aimpf/__init__.py
aimpf/ui.py
aimpf/cli/__init__.py
aimpf/cli/base.py
aimpf/cli/kate_kelly.py
aimpf/cli/nathan_lies.py
aimpf/contrib/__init__.py
aimpf/contrib/kate_kelly/__init__py
aimpf/contrib/kate_kelly/db38pulling.py
aimpf/contrib/nathan_lies/__init__.py
aimpf/contrib/nathan_lies/mechanical/__init__.py
aimpf/contrib/nathan_lies/mechanical/error_analysis.py
aimpf/contrib/nathan_lies/mechanical/fuse.py
aimpf/contrib/nathan_lies/mechanical/tensile.py
aimpf/dispatcher/__init__.py
aimpf/dispatcher/base.py
aimpf/dispatcher/dispatcher.py
aimpf/dispatcher/mqtt.py
aimpf/dispatcher/mysql.py
aimpf/mqtt/__init__.py
aimpf/mqtt/base.py
aimpf/mqtt/formatter.py
aimpf/mqtt/logger.py
aimpf/mqtt/projects.py
aimpf/mqtt/publisher.py
aimpf/mqtt/subscriber.py
aimpf-0.1.10.dist-info/licenses/LICENSE.txt
aimpf-0.1.10.dist-info/METADATA
aimpf-0.1.10.dist-info/WHEEL
aimpf-0.1.10.dist-info/entry_points.txt
aimpf-0.1.10.dist-info/top_level.txt
aimpf-0.1.10.dist-info/RECORD
