Metadata-Version: 2.4
Name: aimpf
Version: 0.1.10
Summary: Library for AIMPF users
Home-page: https://github.com/pyscaffold/pyscaffold/
Author: Branden Kappes
Author-email: branden.kappes@contextualize.us.com
License: MIT
Project-URL: Documentation, https://pyscaffold.org/
Platform: any
Classifier: Development Status :: 4 - Beta
Classifier: Programming Language :: Python
Requires-Python: >=3.11
License-File: LICENSE.txt
Requires-Dist: importlib-metadata
Requires-Dist: matplotlib
Requires-Dist: pycarta
Requires-Dist: python-dotenv
Requires-Dist: pandas
Requires-Dist: scipy
Requires-Dist: shortuuid
Requires-Dist: xlsxwriter
Provides-Extra: testing
Requires-Dist: setuptools; extra == "testing"
Requires-Dist: pytest; extra == "testing"
Requires-Dist: pytest-cov; extra == "testing"
Requires-Dist: pytest-asyncio; extra == "testing"
Requires-Dist: mysql-connector-python; extra == "testing"
Requires-Dist: ipykernel; extra == "testing"
Requires-Dist: flask; extra == "testing"
Dynamic: license-file
